jsonmode/__init__.py
jsonmode/api_client.py
jsonmode/api_response.py
jsonmode/configuration.py
jsonmode/exceptions.py
jsonmode/py.typed
jsonmode/rest.py
jsonmode/api/__init__.py
jsonmode/api/compose_api.py
jsonmode/api/define_api.py
jsonmode/models/__init__.py
jsonmode/models/http_validation_error.py
jsonmode/models/parts.py
jsonmode/models/prompt.py
jsonmode/models/result.py
jsonmode/models/validation_error.py
jsonmode/models/validation_error_loc_inner.py
openapi_client/__init__.py
openapi_client/api_client.py
openapi_client/api_response.py
openapi_client/client.py
openapi_client/configuration.py
openapi_client/exceptions.py
openapi_client/py.typed
openapi_client/rest.py
openapi_client/api/__init__.py
openapi_client/api/compose_api.py
openapi_client/api/define_api.py
openapi_client/models/__init__.py
openapi_client/models/http_validation_error.py
openapi_client/models/parts.py
openapi_client/models/prompt.py
openapi_client/models/result.py
openapi_client/models/validation_error.py
openapi_client/models/validation_error_loc_inner.py
jsonmode-1.0.0.dist-info/METADATA
jsonmode-1.0.0.dist-info/WHEEL
jsonmode-1.0.0.dist-info/top_level.txt
jsonmode-1.0.0.dist-info/RECORD
