Metadata-Version: 2.1
Name: jsonmode
Version: 1.0.0
Summary: JSONmode
Home-page: UNKNOWN
Author: OpenAPI Generator community
Author-email: team@openapitools.org
License: UNKNOWN
Keywords: OpenAPI,OpenAPI-Generator,JSONmode
Platform: UNKNOWN
Requires-Dist: urllib3 (<2.1.0,>=1.25.3)
Requires-Dist: python-dateutil
Requires-Dist: pydantic (>=2)
Requires-Dist: typing-extensions (>=4.7.1)
